agent_toolkit/__init__.py
agent_toolkit/code_collector.py
agent_toolkit/main.py
agent_toolkit/collector/__init__.py
agent_toolkit/collector/analysis.py
agent_toolkit/collector/config.py
agent_toolkit/collector/discovery.py
agent_toolkit/collector/reporting.py
agent_toolkit/collector/utils.py
agent_toolkit/guides/copilot.md
agent_toolkit/guides/cursor.md
agent_toolkit/prompts/specs.md
agent_toolkit/templates/cursor/rules/auto-commit.mdc
agent_toolkit/templates/cursor/rules/global-workflow.mdc
agent_toolkit/templates/cursor/rules/init-project.mdc
agent_toolkit/templates/cursor/rules/init-specs.mdc
agent_toolkit/templates/cursor/rules/init-tasks.mdc
agent_toolkit/templates/cursor/rules/specs-definition.mdc
agent_toolkit/templates/cursor/rules/tasks-definition.mdc
agent_toolkit/templates/github/copilot-instructions.md
agent_toolkit/templates/github/prompts/init-project.prompt.md
agent_toolkit/templates/github/prompts/init-specs.prompt.md
agent_toolkit/templates/github/prompts/init-tasks.prompt.md
agent_toolkit/templates/github/prompts/specs-definition.md
agent_toolkit/templates/github/prompts/tasks-definition.md
agent_toolkit-0.1.9.dist-info/METADATA
agent_toolkit-0.1.9.dist-info/WHEEL
agent_toolkit-0.1.9.dist-info/entry_points.txt
agent_toolkit-0.1.9.dist-info/RECORD
