Metadata-Version: 2.4
Name: agent-toolkit
Version: 0.1.9
Summary: Add your description here
Author-email: Andre Ratzenberger <andre.ratzenberger@whiteduck.de>
Requires-Python: >=3.10
Requires-Dist: flock-core>=0.3.23
Requires-Dist: rich>=13.9.4
Requires-Dist: tomli>=2.0.1
